{
  "apilist": [
    "das_core",
    "fileReplicas4dataset",
    "files_via_dataset"
  ],
  "ctime": 0.047075986862199999,
  "data": [
    {
      "_id": "594b70734bf01c21964e9beb",
      "cache_id": [
        "594b70734bf01c21964e9bdb",
        "594b70734bf01c21964e9bcc"
      ],
      "das": {
        "api": [
          "fileReplicas4dataset",
          "files_via_dataset"
        ],
        "condition_keys": [
          "dataset.name"
        ],
        "expire": 1498116511,
        "instance": "prod/global",
        "primary_key": "file.name",
        "record": 1,
        "services": [
          {
            "phedex": [
              "phedex"
            ]
          },
          {
            "dbs3": [
              "dbs3"
            ]
          }
        ],
        "system": [
          "phedex",
          "dbs3"
        ],
        "ts": 1498116211.9592321
      },
      "das_id": [
        "594b70734bf01c21964e9bbc",
        "594b70734bf01c21964e9bb9"
      ],
      "file": [
        {
          "name": "/store/relval/CMSSW_7_5_0/RelValZpMM_13/GEN-SIM/75X_mcRun2_asymptotic_v1-v1/00000/04A2321C-4A2A-E511-8C70-0025905A6088.root"
        },
        {
          "name": "/store/relval/CMSSW_7_5_0/RelValZpMM_13/GEN-SIM/75X_mcRun2_asymptotic_v1-v1/00000/04A2321C-4A2A-E511-8C70-0025905A6088.root"
        }
      ],
      "qhash": "447e287c6cb18d51bb81d783934e72ae"
    },
    {
      "_id": "594b70734bf01c21964e9bea",
      "cache_id": [
        "594b70734bf01c21964e9bcd",
        "594b70734bf01c21964e9bdc"
      ],
      "das": {
        "api": [
          "fileReplicas4dataset",
          "files_via_dataset"
        ],
        "condition_keys": [
          "dataset.name"
        ],
        "expire": 1498116511,
        "instance": "prod/global",
        "primary_key": "file.name",
        "record": 1,
        "services": [
          {
            "phedex": [
              "phedex"
            ]
          },
          {
            "dbs3": [
              "dbs3"
            ]
          }
        ],
        "system": [
          "phedex",
          "dbs3"
        ],
        "ts": 1498116211.9592321
      },
      "das_id": [
        "594b70734bf01c21964e9bbc",
        "594b70734bf01c21964e9bb9"
      ],
      "file": [
        {
          "name": "/store/relval/CMSSW_7_5_0/RelValZpMM_13/GEN-SIM/75X_mcRun2_asymptotic_v1-v1/00000/7E420D6B-4C2A-E511-9FD5-00261894387C.root"
        },
        {
          "name": "/store/relval/CMSSW_7_5_0/RelValZpMM_13/GEN-SIM/75X_mcRun2_asymptotic_v1-v1/00000/7E420D6B-4C2A-E511-9FD5-00261894387C.root"
        }
      ],
      "qhash": "447e287c6cb18d51bb81d783934e72ae"
    },
    {
      "_id": "594b70734bf01c21964e9be9",
      "cache_id": [
        "594b70734bf01c21964e9bda",
        "594b70734bf01c21964e9bce"
      ],
      "das": {
        "api": [
          "fileReplicas4dataset",
          "files_via_dataset"
        ],
        "condition_keys": [
          "dataset.name"
        ],
        "expire": 1498116511,
        "instance": "prod/global",
        "primary_key": "file.name",
        "record": 1,
        "services": [
          {
            "phedex": [
              "phedex"
            ]
          },
          {
            "dbs3": [
              "dbs3"
            ]
          }
        ],
        "system": [
          "phedex",
          "dbs3"
        ],
        "ts": 1498116211.9592321
      },
      "das_id": [
        "594b70734bf01c21964e9bbc",
        "594b70734bf01c21964e9bb9"
      ],
      "file": [
        {
          "name": "/store/relval/CMSSW_7_5_0/RelValZpMM_13/GEN-SIM/75X_mcRun2_asymptotic_v1-v1/00000/C6E8D766-4C2A-E511-A9FD-0025905A6056.root"
        },
        {
          "name": "/store/relval/CMSSW_7_5_0/RelValZpMM_13/GEN-SIM/75X_mcRun2_asymptotic_v1-v1/00000/C6E8D766-4C2A-E511-A9FD-0025905A6056.root"
        }
      ],
      "qhash": "447e287c6cb18d51bb81d783934e72ae"
    }
  ],
  "incache": true,
  "mongo_query": {
    "fields": [
      "file"
    ],
    "filters": {
      "grep": [
        "file.name"
      ],
      "sort": [],
      "unique": 1
    },
    "instance": "prod/global",
    "qcache": 0,
    "spec": {
      "dataset.name": "/RelValZpMM_13/CMSSW_7_5_0-75X_mcRun2_asymptotic_v1-v1/GEN-SIM"
    }
  },
  "nresults": 3,
  "status": "ok",
  "timestamp": 1498116212.5
}