{
  "apilist": [
    "das_core",
    "file4DatasetRunLumi"
  ],
  "ctime": 0.064682006835900002,
  "data": [
    {
      "_id": "59515e5ef4e3130af1ee3817",
      "cache_id": [
        "59515e5ef4e3130af1ee37c0"
      ],
      "das": {
        "api": [
          "file4DatasetRunLumi"
        ],
        "condition_keys": [
          "run.run_number",
          "dataset.name"
        ],
        "expire": 1498505098,
        "instance": "prod/global",
        "primary_key": "file.name",
        "record": 1,
        "services": [
          {
            "dbs3": [
              "dbs3"
            ]
          }
        ],
        "system": [
          "dbs3"
        ],
        "ts": 1498504798.9530449
      },
      "das_id": [
        "59515e5ef4e3130af1ee3794"
      ],
      "file": [
        {
          "name": "/store/data/Run2016B/MET/RAW/v2/000/274/199/00000/0418D353-BD26-E611-973D-02163E0118B7.root"
        }
      ],
      "qhash": "b8c58cd9320821e2473a7326cdf7de1d"
    },
    {
      "_id": "59515e5ef4e3130af1ee3816",
      "cache_id": [
        "59515e5ef4e3130af1ee37c9"
      ],
      "das": {
        "api": [
          "file4DatasetRunLumi"
        ],
        "condition_keys": [
          "run.run_number",
          "dataset.name"
        ],
        "expire": 1498505098,
        "instance": "prod/global",
        "primary_key": "file.name",
        "record": 1,
        "services": [
          {
            "dbs3": [
              "dbs3"
            ]
          }
        ],
        "system": [
          "dbs3"
        ],
        "ts": 1498504798.9530449
      },
      "das_id": [
        "59515e5ef4e3130af1ee3794"
      ],
      "file": [
        {
          "name": "/store/data/Run2016B/MET/RAW/v2/000/274/199/00000/14705311-BD26-E611-94A1-02163E014145.root"
        }
      ],
      "qhash": "b8c58cd9320821e2473a7326cdf7de1d"
    },
    {
      "_id": "59515e5ef4e3130af1ee3815",
      "cache_id": [
        "59515e5ef4e3130af1ee37b2"
      ],
      "das": {
        "api": [
          "file4DatasetRunLumi"
        ],
        "condition_keys": [
          "run.run_number",
          "dataset.name"
        ],
        "expire": 1498505098,
        "instance": "prod/global",
        "primary_key": "file.name",
        "record": 1,
        "services": [
          {
            "dbs3": [
              "dbs3"
            ]
          }
        ],
        "system": [
          "dbs3"
        ],
        "ts": 1498504798.9530449
      },
      "das_id": [
        "59515e5ef4e3130af1ee3794"
      ],
      "file": [
        {
          "name": "/store/data/Run2016B/MET/RAW/v2/000/274/199/00000/14A0D662-BD26-E611-B2B1-02163E012293.root"
        }
      ],
      "qhash": "b8c58cd9320821e2473a7326cdf7de1d"
    },
    {
      "_id": "59515e5ef4e3130af1ee3814",
      "cache_id": [
        "59515e5ef4e3130af1ee37cb"
      ],
      "das": {
        "api": [
          "file4DatasetRunLumi"
        ],
        "condition_keys": [
          "run.run_number",
          "dataset.name"
        ],
        "expire": 1498505098,
        "instance": "prod/global",
        "primary_key": "file.name",
        "record": 1,
        "services": [
          {
            "dbs3": [
              "dbs3"
            ]
          }
        ],
        "system": [
          "dbs3"
        ],
        "ts": 1498504798.9530449
      },
      "das_id": [
        "59515e5ef4e3130af1ee3794"
      ],
      "file": [
        {
          "name": "/store/data/Run2016B/MET/RAW/v2/000/274/199/00000/18F15B33-BD26-E611-86DB-02163E011B90.root"
        }
      ],
      "qhash": "b8c58cd9320821e2473a7326cdf7de1d"
    },
    {
      "_id": "59515e5ef4e3130af1ee3813",
      "cache_id": [
        "59515e5ef4e3130af1ee37cc"
      ],
      "das": {
        "api": [
          "file4DatasetRunLumi"
        ],
        "condition_keys": [
          "run.run_number",
          "dataset.name"
        ],
        "expire": 1498505098,
        "instance": "prod/global",
        "primary_key": "file.name",
        "record": 1,
        "services": [
          {
            "dbs3": [
              "dbs3"
            ]
          }
        ],
        "system": [
          "dbs3"
        ],
        "ts": 1498504798.9530449
      },
      "das_id": [
        "59515e5ef4e3130af1ee3794"
      ],
      "file": [
        {
          "name": "/store/data/Run2016B/MET/RAW/v2/000/274/199/00000/1EAAC14F-BD26-E611-B97D-02163E011E55.root"
        }
      ],
      "qhash": "b8c58cd9320821e2473a7326cdf7de1d"
    },
    {
      "_id": "59515e5ef4e3130af1ee3812",
      "cache_id": [
        "59515e5ef4e3130af1ee37ab"
      ],
      "das": {
        "api": [
          "file4DatasetRunLumi"
        ],
        "condition_keys": [
          "run.run_number",
          "dataset.name"
        ],
        "expire": 1498505098,
        "instance": "prod/global",
        "primary_key": "file.name",
        "record": 1,
        "services": [
          {
            "dbs3": [
              "dbs3"
            ]
          }
        ],
        "system": [
          "dbs3"
        ],
        "ts": 1498504798.9530449
      },
      "das_id": [
        "59515e5ef4e3130af1ee3794"
      ],
      "file": [
        {
          "name": "/store/data/Run2016B/MET/RAW/v2/000/274/199/00000/28546719-BD26-E611-8775-02163E0134A7.root"
        }
      ],
      "qhash": "b8c58cd9320821e2473a7326cdf7de1d"
    },
    {
      "_id": "59515e5ef4e3130af1ee3811",
      "cache_id": [
        "59515e5ef4e3130af1ee37a3"
      ],
      "das": {
        "api": [
          "file4DatasetRunLumi"
        ],
        "condition_keys": [
          "run.run_number",
          "dataset.name"
        ],
        "expire": 1498505098,
        "instance": "prod/global",
        "primary_key": "file.name",
        "record": 1,
        "services": [
          {
            "dbs3": [
              "dbs3"
            ]
          }
        ],
        "system": [
          "dbs3"
        ],
        "ts": 1498504798.9530449
      },
      "das_id": [
        "59515e5ef4e3130af1ee3794"
      ],
      "file": [
        {
          "name": "/store/data/Run2016B/MET/RAW/v2/000/274/199/00000/28901548-BD26-E611-A3C3-02163E014131.root"
        }
      ],
      "qhash": "b8c58cd9320821e2473a7326cdf7de1d"
    },
    {
      "_id": "59515e5ef4e3130af1ee3810",
      "cache_id": [
        "59515e5ef4e3130af1ee37a9"
      ],
      "das": {
        "api": [
          "file4DatasetRunLumi"
        ],
        "condition_keys": [
          "run.run_number",
          "dataset.name"
        ],
        "expire": 1498505098,
        "instance": "prod/global",
        "primary_key": "file.name",
        "record": 1,
        "services": [
          {
            "dbs3": [
              "dbs3"
            ]
          }
        ],
        "system": [
          "dbs3"
        ],
        "ts": 1498504798.9530449
      },
      "das_id": [
        "59515e5ef4e3130af1ee3794"
      ],
      "file": [
        {
          "name": "/store/data/Run2016B/MET/RAW/v2/000/274/199/00000/32C82889-BD26-E611-8638-02163E01254F.root"
        }
      ],
      "qhash": "b8c58cd9320821e2473a7326cdf7de1d"
    },
    {
      "_id": "59515e5ef4e3130af1ee380f",
      "cache_id": [
        "59515e5ef4e3130af1ee37d1"
      ],
      "das": {
        "api": [
          "file4DatasetRunLumi"
        ],
        "condition_keys": [
          "run.run_number",
          "dataset.name"
        ],
        "expire": 1498505098,
        "instance": "prod/global",
        "primary_key": "file.name",
        "record": 1,
        "services": [
          {
            "dbs3": [
              "dbs3"
            ]
          }
        ],
        "system": [
          "dbs3"
        ],
        "ts": 1498504798.9530449
      },
      "das_id": [
        "59515e5ef4e3130af1ee3794"
      ],
      "file": [
        {
          "name": "/store/data/Run2016B/MET/RAW/v2/000/274/199/00000/34B29882-BD26-E611-91D0-02163E013527.root"
        }
      ],
      "qhash": "b8c58cd9320821e2473a7326cdf7de1d"
    },
    {
      "_id": "59515e5ef4e3130af1ee380e",
      "cache_id": [
        "59515e5ef4e3130af1ee37c3"
      ],
      "das": {
        "api": [
          "file4DatasetRunLumi"
        ],
        "condition_keys": [
          "run.run_number",
          "dataset.name"
        ],
        "expire": 1498505098,
        "instance": "prod/global",
        "primary_key": "file.name",
        "record": 1,
        "services": [
          {
            "dbs3": [
              "dbs3"
            ]
          }
        ],
        "system": [
          "dbs3"
        ],
        "ts": 1498504798.9530449
      },
      "das_id": [
        "59515e5ef4e3130af1ee3794"
      ],
      "file": [
        {
          "name": "/store/data/Run2016B/MET/RAW/v2/000/274/199/00000/3E647887-BD26-E611-AA80-02163E01424B.root"
        }
      ],
      "qhash": "b8c58cd9320821e2473a7326cdf7de1d"
    },
    {
      "_id": "59515e5ef4e3130af1ee380d",
      "cache_id": [
        "59515e5ef4e3130af1ee37b7"
      ],
      "das": {
        "api": [
          "file4DatasetRunLumi"
        ],
        "condition_keys": [
          "run.run_number",
          "dataset.name"
        ],
        "expire": 1498505098,
        "instance": "prod/global",
        "primary_key": "file.name",
        "record": 1,
        "services": [
          {
            "dbs3": [
              "dbs3"
            ]
          }
        ],
        "system": [
          "dbs3"
        ],
        "ts": 1498504798.9530449
      },
      "das_id": [
        "59515e5ef4e3130af1ee3794"
      ],
      "file": [
        {
          "name": "/store/data/Run2016B/MET/RAW/v2/000/274/199/00000/4285CD3A-BD26-E611-B107-02163E012694.root"
        }
      ],
      "qhash": "b8c58cd9320821e2473a7326cdf7de1d"
    },
    {
      "_id": "59515e5ef4e3130af1ee380c",
      "cache_id": [
        "59515e5ef4e3130af1ee37b1"
      ],
      "das": {
        "api": [
          "file4DatasetRunLumi"
        ],
        "condition_keys": [
          "run.run_number",
          "dataset.name"
        ],
        "expire": 1498505098,
        "instance": "prod/global",
        "primary_key": "file.name",
        "record": 1,
        "services": [
          {
            "dbs3": [
              "dbs3"
            ]
          }
        ],
        "system": [
          "dbs3"
        ],
        "ts": 1498504798.9530449
      },
      "das_id": [
        "59515e5ef4e3130af1ee3794"
      ],
      "file": [
        {
          "name": "/store/data/Run2016B/MET/RAW/v2/000/274/199/00000/46FFF24B-BD26-E611-8A33-02163E0143E7.root"
        }
      ],
      "qhash": "b8c58cd9320821e2473a7326cdf7de1d"
    },
    {
      "_id": "59515e5ef4e3130af1ee380b",
      "cache_id": [
        "59515e5ef4e3130af1ee37bf"
      ],
      "das": {
        "api": [
          "file4DatasetRunLumi"
        ],
        "condition_keys": [
          "run.run_number",
          "dataset.name"
        ],
        "expire": 1498505098,
        "instance": "prod/global",
        "primary_key": "file.name",
        "record": 1,
        "services": [
          {
            "dbs3": [
              "dbs3"
            ]
          }
        ],
        "system": [
          "dbs3"
        ],
        "ts": 1498504798.9530449
      },
      "das_id": [
        "59515e5ef4e3130af1ee3794"
      ],
      "file": [
        {
          "name": "/store/data/Run2016B/MET/RAW/v2/000/274/199/00000/4E43694D-BD26-E611-A212-02163E014648.root"
        }
      ],
      "qhash": "b8c58cd9320821e2473a7326cdf7de1d"
    },
    {
      "_id": "59515e5ef4e3130af1ee380a",
      "cache_id": [
        "59515e5ef4e3130af1ee37cf"
      ],
      "das": {
        "api": [
          "file4DatasetRunLumi"
        ],
        "condition_keys": [
          "run.run_number",
          "dataset.name"
        ],
        "expire": 1498505098,
        "instance": "prod/global",
        "primary_key": "file.name",
        "record": 1,
        "services": [
          {
            "dbs3": [
              "dbs3"
            ]
          }
        ],
        "system": [
          "dbs3"
        ],
        "ts": 1498504798.9530449
      },
      "das_id": [
        "59515e5ef4e3130af1ee3794"
      ],
      "file": [
        {
          "name": "/store/data/Run2016B/MET/RAW/v2/000/274/199/00000/54A3AF4B-BD26-E611-AA6D-02163E0141C3.root"
        }
      ],
      "qhash": "b8c58cd9320821e2473a7326cdf7de1d"
    },
    {
      "_id": "59515e5ef4e3130af1ee3809",
      "cache_id": [
        "59515e5ef4e3130af1ee37bd"
      ],
      "das": {
        "api": [
          "file4DatasetRunLumi"
        ],
        "condition_keys": [
          "run.run_number",
          "dataset.name"
        ],
        "expire": 1498505098,
        "instance": "prod/global",
        "primary_key": "file.name",
        "record": 1,
        "services": [
          {
            "dbs3": [
              "dbs3"
            ]
          }
        ],
        "system": [
          "dbs3"
        ],
        "ts": 1498504798.9530449
      },
      "das_id": [
        "59515e5ef4e3130af1ee3794"
      ],
      "file": [
        {
          "name": "/store/data/Run2016B/MET/RAW/v2/000/274/199/00000/564E7E11-BD26-E611-8864-02163E01431E.root"
        }
      ],
      "qhash": "b8c58cd9320821e2473a7326cdf7de1d"
    },
    {
      "_id": "59515e5ef4e3130af1ee3808",
      "cache_id": [
        "59515e5ef4e3130af1ee37c2"
      ],
      "das": {
        "api": [
          "file4DatasetRunLumi"
        ],
        "condition_keys": [
          "run.run_number",
          "dataset.name"
        ],
        "expire": 1498505098,
        "instance": "prod/global",
        "primary_key": "file.name",
        "record": 1,
        "services": [
          {
            "dbs3": [
              "dbs3"
            ]
          }
        ],
        "system": [
          "dbs3"
        ],
        "ts": 1498504798.9530449
      },
      "das_id": [
        "59515e5ef4e3130af1ee3794"
      ],
      "file": [
        {
          "name": "/store/data/Run2016B/MET/RAW/v2/000/274/199/00000/6461AA41-BD26-E611-B3F1-02163E014724.root"
        }
      ],
      "qhash": "b8c58cd9320821e2473a7326cdf7de1d"
    },
    {
      "_id": "59515e5ef4e3130af1ee3807",
      "cache_id": [
        "59515e5ef4e3130af1ee37b4"
      ],
      "das": {
        "api": [
          "file4DatasetRunLumi"
        ],
        "condition_keys": [
          "run.run_number",
          "dataset.name"
        ],
        "expire": 1498505098,
        "instance": "prod/global",
        "primary_key": "file.name",
        "record": 1,
        "services": [
          {
            "dbs3": [
              "dbs3"
            ]
          }
        ],
        "system": [
          "dbs3"
        ],
        "ts": 1498504798.9530449
      },
      "das_id": [
        "59515e5ef4e3130af1ee3794"
      ],
      "file": [
        {
          "name": "/store/data/Run2016B/MET/RAW/v2/000/274/199/00000/64CFC215-BD26-E611-A5E0-02163E011E13.root"
        }
      ],
      "qhash": "b8c58cd9320821e2473a7326cdf7de1d"
    },
    {
      "_id": "59515e5ef4e3130af1ee3806",
      "cache_id": [
        "59515e5ef4e3130af1ee37b9"
      ],
      "das": {
        "api": [
          "file4DatasetRunLumi"
        ],
        "condition_keys": [
          "run.run_number",
          "dataset.name"
        ],
        "expire": 1498505098,
        "instance": "prod/global",
        "primary_key": "file.name",
        "record": 1,
        "services": [
          {
            "dbs3": [
              "dbs3"
            ]
          }
        ],
        "system": [
          "dbs3"
        ],
        "ts": 1498504798.9530449
      },
      "das_id": [
        "59515e5ef4e3130af1ee3794"
      ],
      "file": [
        {
          "name": "/store/data/Run2016B/MET/RAW/v2/000/274/199/00000/66A4D571-BD26-E611-B415-02163E0127A7.root"
        }
      ],
      "qhash": "b8c58cd9320821e2473a7326cdf7de1d"
    },
    {
      "_id": "59515e5ef4e3130af1ee3805",
      "cache_id": [
        "59515e5ef4e3130af1ee37a6"
      ],
      "das": {
        "api": [
          "file4DatasetRunLumi"
        ],
        "condition_keys": [
          "run.run_number",
          "dataset.name"
        ],
        "expire": 1498505098,
        "instance": "prod/global",
        "primary_key": "file.name",
        "record": 1,
        "services": [
          {
            "dbs3": [
              "dbs3"
            ]
          }
        ],
        "system": [
          "dbs3"
        ],
        "ts": 1498504798.9530449
      },
      "das_id": [
        "59515e5ef4e3130af1ee3794"
      ],
      "file": [
        {
          "name": "/store/data/Run2016B/MET/RAW/v2/000/274/199/00000/6C226563-BD26-E611-82E7-02163E0133A8.root"
        }
      ],
      "qhash": "b8c58cd9320821e2473a7326cdf7de1d"
    },
    {
      "_id": "59515e5ef4e3130af1ee3804",
      "cache_id": [
        "59515e5ef4e3130af1ee37bb"
      ],
      "das": {
        "api": [
          "file4DatasetRunLumi"
        ],
        "condition_keys": [
          "run.run_number",
          "dataset.name"
        ],
        "expire": 1498505098,
        "instance": "prod/global",
        "primary_key": "file.name",
        "record": 1,
        "services": [
          {
            "dbs3": [
              "dbs3"
            ]
          }
        ],
        "system": [
          "dbs3"
        ],
        "ts": 1498504798.9530449
      },
      "das_id": [
        "59515e5ef4e3130af1ee3794"
      ],
      "file": [
        {
          "name": "/store/data/Run2016B/MET/RAW/v2/000/274/199/00000/6E40A184-BD26-E611-9A4D-02163E01469B.root"
        }
      ],
      "qhash": "b8c58cd9320821e2473a7326cdf7de1d"
    },
    {
      "_id": "59515e5ef4e3130af1ee3803",
      "cache_id": [
        "59515e5ef4e3130af1ee37b3"
      ],
      "das": {
        "api": [
          "file4DatasetRunLumi"
        ],
        "condition_keys": [
          "run.run_number",
          "dataset.name"
        ],
        "expire": 1498505098,
        "instance": "prod/global",
        "primary_key": "file.name",
        "record": 1,
        "services": [
          {
            "dbs3": [
              "dbs3"
            ]
          }
        ],
        "system": [
          "dbs3"
        ],
        "ts": 1498504798.9530449
      },
      "das_id": [
        "59515e5ef4e3130af1ee3794"
      ],
      "file": [
        {
          "name": "/store/data/Run2016B/MET/RAW/v2/000/274/199/00000/6E64670E-BD26-E611-94BD-02163E0146F3.root"
        }
      ],
      "qhash": "b8c58cd9320821e2473a7326cdf7de1d"
    },
    {
      "_id": "59515e5ef4e3130af1ee3802",
      "cache_id": [
        "59515e5ef4e3130af1ee37bc"
      ],
      "das": {
        "api": [
          "file4DatasetRunLumi"
        ],
        "condition_keys": [
          "run.run_number",
          "dataset.name"
        ],
        "expire": 1498505098,
        "instance": "prod/global",
        "primary_key": "file.name",
        "record": 1,
        "services": [
          {
            "dbs3": [
              "dbs3"
            ]
          }
        ],
        "system": [
          "dbs3"
        ],
        "ts": 1498504798.9530449
      },
      "das_id": [
        "59515e5ef4e3130af1ee3794"
      ],
      "file": [
        {
          "name": "/store/data/Run2016B/MET/RAW/v2/000/274/199/00000/6ED9181F-BD26-E611-8ACA-02163E0125D8.root"
        }
      ],
      "qhash": "b8c58cd9320821e2473a7326cdf7de1d"
    },
    {
      "_id": "59515e5ef4e3130af1ee3801",
      "cache_id": [
        "59515e5ef4e3130af1ee37a7"
      ],
      "das": {
        "api": [
          "file4DatasetRunLumi"
        ],
        "condition_keys": [
          "run.run_number",
          "dataset.name"
        ],
        "expire": 1498505098,
        "instance": "prod/global",
        "primary_key": "file.name",
        "record": 1,
        "services": [
          {
            "dbs3": [
              "dbs3"
            ]
          }
        ],
        "system": [
          "dbs3"
        ],
        "ts": 1498504798.9530449
      },
      "das_id": [
        "59515e5ef4e3130af1ee3794"
      ],
      "file": [
        {
          "name": "/store/data/Run2016B/MET/RAW/v2/000/274/199/00000/723C3064-BD26-E611-949C-02163E0127F5.root"
        }
      ],
      "qhash": "b8c58cd9320821e2473a7326cdf7de1d"
    },
    {
      "_id": "59515e5ef4e3130af1ee3800",
      "cache_id": [
        "59515e5ef4e3130af1ee37c4"
      ],
      "das": {
        "api": [
          "file4DatasetRunLumi"
        ],
        "condition_keys": [
          "run.run_number",
          "dataset.name"
        ],
        "expire": 1498505098,
        "instance": "prod/global",
        "primary_key": "file.name",
        "record": 1,
        "services": [
          {
            "dbs3": [
              "dbs3"
            ]
          }
        ],
        "system": [
          "dbs3"
        ],
        "ts": 1498504798.9530449
      },
      "das_id": [
        "59515e5ef4e3130af1ee3794"
      ],
      "file": [
        {
          "name": "/store/data/Run2016B/MET/RAW/v2/000/274/199/00000/72B31585-BD26-E611-924B-02163E01446B.root"
        }
      ],
      "qhash": "b8c58cd9320821e2473a7326cdf7de1d"
    },
    {
      "_id": "59515e5ef4e3130af1ee37ff",
      "cache_id": [
        "59515e5ef4e3130af1ee37ca"
      ],
      "das": {
        "api": [
          "file4DatasetRunLumi"
        ],
        "condition_keys": [
          "run.run_number",
          "dataset.name"
        ],
        "expire": 1498505098,
        "instance": "prod/global",
        "primary_key": "file.name",
        "record": 1,
        "services": [
          {
            "dbs3": [
              "dbs3"
            ]
          }
        ],
        "system": [
          "dbs3"
        ],
        "ts": 1498504798.9530449
      },
      "das_id": [
        "59515e5ef4e3130af1ee3794"
      ],
      "file": [
        {
          "name": "/store/data/Run2016B/MET/RAW/v2/000/274/199/00000/785AE413-BD26-E611-8809-02163E013989.root"
        }
      ],
      "qhash": "b8c58cd9320821e2473a7326cdf7de1d"
    },
    {
      "_id": "59515e5ef4e3130af1ee37fe",
      "cache_id": [
        "59515e5ef4e3130af1ee37af"
      ],
      "das": {
        "api": [
          "file4DatasetRunLumi"
        ],
        "condition_keys": [
          "run.run_number",
          "dataset.name"
        ],
        "expire": 1498505098,
        "instance": "prod/global",
        "primary_key": "file.name",
        "record": 1,
        "services": [
          {
            "dbs3": [
              "dbs3"
            ]
          }
        ],
        "system": [
          "dbs3"
        ],
        "ts": 1498504798.9530449
      },
      "das_id": [
        "59515e5ef4e3130af1ee3794"
      ],
      "file": [
        {
          "name": "/store/data/Run2016B/MET/RAW/v2/000/274/199/00000/7A158D17-BD26-E611-A731-02163E012BE5.root"
        }
      ],
      "qhash": "b8c58cd9320821e2473a7326cdf7de1d"
    },
    {
      "_id": "59515e5ef4e3130af1ee37fd",
      "cache_id": [
        "59515e5ef4e3130af1ee37c8"
      ],
      "das": {
        "api": [
          "file4DatasetRunLumi"
        ],
        "condition_keys": [
          "run.run_number",
          "dataset.name"
        ],
        "expire": 1498505098,
        "instance": "prod/global",
        "primary_key": "file.name",
        "record": 1,
        "services": [
          {
            "dbs3": [
              "dbs3"
            ]
          }
        ],
        "system": [
          "dbs3"
        ],
        "ts": 1498504798.9530449
      },
      "das_id": [
        "59515e5ef4e3130af1ee3794"
      ],
      "file": [
        {
          "name": "/store/data/Run2016B/MET/RAW/v2/000/274/199/00000/7E1F0712-BD26-E611-922F-02163E011EE5.root"
        }
      ],
      "qhash": "b8c58cd9320821e2473a7326cdf7de1d"
    },
    {
      "_id": "59515e5ef4e3130af1ee37fc",
      "cache_id": [
        "59515e5ef4e3130af1ee37a8"
      ],
      "das": {
        "api": [
          "file4DatasetRunLumi"
        ],
        "condition_keys": [
          "run.run_number",
          "dataset.name"
        ],
        "expire": 1498505098,
        "instance": "prod/global",
        "primary_key": "file.name",
        "record": 1,
        "services": [
          {
            "dbs3": [
              "dbs3"
            ]
          }
        ],
        "system": [
          "dbs3"
        ],
        "ts": 1498504798.9530449
      },
      "das_id": [
        "59515e5ef4e3130af1ee3794"
      ],
      "file": [
        {
          "name": "/store/data/Run2016B/MET/RAW/v2/000/274/199/00000/963206BA-BD26-E611-81B7-02163E0143ED.root"
        }
      ],
      "qhash": "b8c58cd9320821e2473a7326cdf7de1d"
    },
    {
      "_id": "59515e5ef4e3130af1ee37fb",
      "cache_id": [
        "59515e5ef4e3130af1ee37d6"
      ],
      "das": {
        "api": [
          "file4DatasetRunLumi"
        ],
        "condition_keys": [
          "run.run_number",
          "dataset.name"
        ],
        "expire": 1498505098,
        "instance": "prod/global",
        "primary_key": "file.name",
        "record": 1,
        "services": [
          {
            "dbs3": [
              "dbs3"
            ]
          }
        ],
        "system": [
          "dbs3"
        ],
        "ts": 1498504798.9530449
      },
      "das_id": [
        "59515e5ef4e3130af1ee3794"
      ],
      "file": [
        {
          "name": "/store/data/Run2016B/MET/RAW/v2/000/274/199/00000/A418680F-BD26-E611-87DF-02163E0134D9.root"
        }
      ],
      "qhash": "b8c58cd9320821e2473a7326cdf7de1d"
    },
    {
      "_id": "59515e5ef4e3130af1ee37fa",
      "cache_id": [
        "59515e5ef4e3130af1ee37aa"
      ],
      "das": {
        "api": [
          "file4DatasetRunLumi"
        ],
        "condition_keys": [
          "run.run_number",
          "dataset.name"
        ],
        "expire": 1498505098,
        "instance": "prod/global",
        "primary_key": "file.name",
        "record": 1,
        "services": [
          {
            "dbs3": [
              "dbs3"
            ]
          }
        ],
        "system": [
          "dbs3"
        ],
        "ts": 1498504798.9530449
      },
      "das_id": [
        "59515e5ef4e3130af1ee3794"
      ],
      "file": [
        {
          "name": "/store/data/Run2016B/MET/RAW/v2/000/274/199/00000/A6004A25-BD26-E611-8611-02163E01416B.root"
        }
      ],
      "qhash": "b8c58cd9320821e2473a7326cdf7de1d"
    },
    {
      "_id": "59515e5ef4e3130af1ee37f9",
      "cache_id": [
        "59515e5ef4e3130af1ee37a2"
      ],
      "das": {
        "api": [
          "file4DatasetRunLumi"
        ],
        "condition_keys": [
          "run.run_number",
          "dataset.name"
        ],
        "expire": 1498505098,
        "instance": "prod/global",
        "primary_key": "file.name",
        "record": 1,
        "services": [
          {
            "dbs3": [
              "dbs3"
            ]
          }
        ],
        "system": [
          "dbs3"
        ],
        "ts": 1498504798.9530449
      },
      "das_id": [
        "59515e5ef4e3130af1ee3794"
      ],
      "file": [
        {
          "name": "/store/data/Run2016B/MET/RAW/v2/000/274/199/00000/A645EB5C-BD26-E611-BD2B-02163E014589.root"
        }
      ],
      "qhash": "b8c58cd9320821e2473a7326cdf7de1d"
    },
    {
      "_id": "59515e5ef4e3130af1ee37f8",
      "cache_id": [
        "59515e5ef4e3130af1ee37d2"
      ],
      "das": {
        "api": [
          "file4DatasetRunLumi"
        ],
        "condition_keys": [
          "run.run_number",
          "dataset.name"
        ],
        "expire": 1498505098,
        "instance": "prod/global",
        "primary_key": "file.name",
        "record": 1,
        "services": [
          {
            "dbs3": [
              "dbs3"
            ]
          }
        ],
        "system": [
          "dbs3"
        ],
        "ts": 1498504798.9530449
      },
      "das_id": [
        "59515e5ef4e3130af1ee3794"
      ],
      "file": [
        {
          "name": "/store/data/Run2016B/MET/RAW/v2/000/274/199/00000/AA5CCB52-BD26-E611-BDDE-02163E012453.root"
        }
      ],
      "qhash": "b8c58cd9320821e2473a7326cdf7de1d"
    },
    {
      "_id": "59515e5ef4e3130af1ee37f7",
      "cache_id": [
        "59515e5ef4e3130af1ee37ce"
      ],
      "das": {
        "api": [
          "file4DatasetRunLumi"
        ],
        "condition_keys": [
          "run.run_number",
          "dataset.name"
        ],
        "expire": 1498505098,
        "instance": "prod/global",
        "primary_key": "file.name",
        "record": 1,
        "services": [
          {
            "dbs3": [
              "dbs3"
            ]
          }
        ],
        "system": [
          "dbs3"
        ],
        "ts": 1498504798.9530449
      },
      "das_id": [
        "59515e5ef4e3130af1ee3794"
      ],
      "file": [
        {
          "name": "/store/data/Run2016B/MET/RAW/v2/000/274/199/00000/B6CE6341-BD26-E611-990C-02163E014649.root"
        }
      ],
      "qhash": "b8c58cd9320821e2473a7326cdf7de1d"
    },
    {
      "_id": "59515e5ef4e3130af1ee37f6",
      "cache_id": [
        "59515e5ef4e3130af1ee37be"
      ],
      "das": {
        "api": [
          "file4DatasetRunLumi"
        ],
        "condition_keys": [
          "run.run_number",
          "dataset.name"
        ],
        "expire": 1498505098,
        "instance": "prod/global",
        "primary_key": "file.name",
        "record": 1,
        "services": [
          {
            "dbs3": [
              "dbs3"
            ]
          }
        ],
        "system": [
          "dbs3"
        ],
        "ts": 1498504798.9530449
      },
      "das_id": [
        "59515e5ef4e3130af1ee3794"
      ],
      "file": [
        {
          "name": "/store/data/Run2016B/MET/RAW/v2/000/274/199/00000/B8991176-BD26-E611-B298-02163E01356B.root"
        }
      ],
      "qhash": "b8c58cd9320821e2473a7326cdf7de1d"
    },
    {
      "_id": "59515e5ef4e3130af1ee37f5",
      "cache_id": [
        "59515e5ef4e3130af1ee37c1"
      ],
      "das": {
        "api": [
          "file4DatasetRunLumi"
        ],
        "condition_keys": [
          "run.run_number",
          "dataset.name"
        ],
        "expire": 1498505098,
        "instance": "prod/global",
        "primary_key": "file.name",
        "record": 1,
        "services": [
          {
            "dbs3": [
              "dbs3"
            ]
          }
        ],
        "system": [
          "dbs3"
        ],
        "ts": 1498504798.9530449
      },
      "das_id": [
        "59515e5ef4e3130af1ee3794"
      ],
      "file": [
        {
          "name": "/store/data/Run2016B/MET/RAW/v2/000/274/199/00000/B8B4FB16-BD26-E611-A129-02163E0141B4.root"
        }
      ],
      "qhash": "b8c58cd9320821e2473a7326cdf7de1d"
    },
    {
      "_id": "59515e5ef4e3130af1ee37f4",
      "cache_id": [
        "59515e5ef4e3130af1ee37b6"
      ],
      "das": {
        "api": [
          "file4DatasetRunLumi"
        ],
        "condition_keys": [
          "run.run_number",
          "dataset.name"
        ],
        "expire": 1498505098,
        "instance": "prod/global",
        "primary_key": "file.name",
        "record": 1,
        "services": [
          {
            "dbs3": [
              "dbs3"
            ]
          }
        ],
        "system": [
          "dbs3"
        ],
        "ts": 1498504798.9530449
      },
      "das_id": [
        "59515e5ef4e3130af1ee3794"
      ],
      "file": [
        {
          "name": "/store/data/Run2016B/MET/RAW/v2/000/274/199/00000/B8DF9916-BD26-E611-8CEB-02163E014207.root"
        }
      ],
      "qhash": "b8c58cd9320821e2473a7326cdf7de1d"
    },
    {
      "_id": "59515e5ef4e3130af1ee37f3",
      "cache_id": [
        "59515e5ef4e3130af1ee37a5"
      ],
      "das": {
        "api": [
          "file4DatasetRunLumi"
        ],
        "condition_keys": [
          "run.run_number",
          "dataset.name"
        ],
        "expire": 1498505098,
        "instance": "prod/global",
        "primary_key": "file.name",
        "record": 1,
        "services": [
          {
            "dbs3": [
              "dbs3"
            ]
          }
        ],
        "system": [
          "dbs3"
        ],
        "ts": 1498504798.9530449
      },
      "das_id": [
        "59515e5ef4e3130af1ee3794"
      ],
      "file": [
        {
          "name": "/store/data/Run2016B/MET/RAW/v2/000/274/199/00000/BC9A4B5A-BD26-E611-89BF-02163E0136B3.root"
        }
      ],
      "qhash": "b8c58cd9320821e2473a7326cdf7de1d"
    },
    {
      "_id": "59515e5ef4e3130af1ee37f2",
      "cache_id": [
        "59515e5ef4e3130af1ee37c5"
      ],
      "das": {
        "api": [
          "file4DatasetRunLumi"
        ],
        "condition_keys": [
          "run.run_number",
          "dataset.name"
        ],
        "expire": 1498505098,
        "instance": "prod/global",
        "primary_key": "file.name",
        "record": 1,
        "services": [
          {
            "dbs3": [
              "dbs3"
            ]
          }
        ],
        "system": [
          "dbs3"
        ],
        "ts": 1498504798.9530449
      },
      "das_id": [
        "59515e5ef4e3130af1ee3794"
      ],
      "file": [
        {
          "name": "/store/data/Run2016B/MET/RAW/v2/000/274/199/00000/BCAB5571-BD26-E611-8A90-02163E0144E3.root"
        }
      ],
      "qhash": "b8c58cd9320821e2473a7326cdf7de1d"
    },
    {
      "_id": "59515e5ef4e3130af1ee37f1",
      "cache_id": [
        "59515e5ef4e3130af1ee37ad"
      ],
      "das": {
        "api": [
          "file4DatasetRunLumi"
        ],
        "condition_keys": [
          "run.run_number",
          "dataset.name"
        ],
        "expire": 1498505098,
        "instance": "prod/global",
        "primary_key": "file.name",
        "record": 1,
        "services": [
          {
            "dbs3": [
              "dbs3"
            ]
          }
        ],
        "system": [
          "dbs3"
        ],
        "ts": 1498504798.9530449
      },
      "das_id": [
        "59515e5ef4e3130af1ee3794"
      ],
      "file": [
        {
          "name": "/store/data/Run2016B/MET/RAW/v2/000/274/199/00000/BCCFAD8B-BD26-E611-8A84-02163E012BD3.root"
        }
      ],
      "qhash": "b8c58cd9320821e2473a7326cdf7de1d"
    },
    {
      "_id": "59515e5ef4e3130af1ee37f0",
      "cache_id": [
        "59515e5ef4e3130af1ee37d4"
      ],
      "das": {
        "api": [
          "file4DatasetRunLumi"
        ],
        "condition_keys": [
          "run.run_number",
          "dataset.name"
        ],
        "expire": 1498505098,
        "instance": "prod/global",
        "primary_key": "file.name",
        "record": 1,
        "services": [
          {
            "dbs3": [
              "dbs3"
            ]
          }
        ],
        "system": [
          "dbs3"
        ],
        "ts": 1498504798.9530449
      },
      "das_id": [
        "59515e5ef4e3130af1ee3794"
      ],
      "file": [
        {
          "name": "/store/data/Run2016B/MET/RAW/v2/000/274/199/00000/BE16A18B-BD26-E611-8E12-02163E01381B.root"
        }
      ],
      "qhash": "b8c58cd9320821e2473a7326cdf7de1d"
    },
    {
      "_id": "59515e5ef4e3130af1ee37ef",
      "cache_id": [
        "59515e5ef4e3130af1ee37d0"
      ],
      "das": {
        "api": [
          "file4DatasetRunLumi"
        ],
        "condition_keys": [
          "run.run_number",
          "dataset.name"
        ],
        "expire": 1498505098,
        "instance": "prod/global",
        "primary_key": "file.name",
        "record": 1,
        "services": [
          {
            "dbs3": [
              "dbs3"
            ]
          }
        ],
        "system": [
          "dbs3"
        ],
        "ts": 1498504798.9530449
      },
      "das_id": [
        "59515e5ef4e3130af1ee3794"
      ],
      "file": [
        {
          "name": "/store/data/Run2016B/MET/RAW/v2/000/274/199/00000/BEA3C84F-BD26-E611-8872-02163E014418.root"
        }
      ],
      "qhash": "b8c58cd9320821e2473a7326cdf7de1d"
    },
    {
      "_id": "59515e5ef4e3130af1ee37ee",
      "cache_id": [
        "59515e5ef4e3130af1ee37cd"
      ],
      "das": {
        "api": [
          "file4DatasetRunLumi"
        ],
        "condition_keys": [
          "run.run_number",
          "dataset.name"
        ],
        "expire": 1498505098,
        "instance": "prod/global",
        "primary_key": "file.name",
        "record": 1,
        "services": [
          {
            "dbs3": [
              "dbs3"
            ]
          }
        ],
        "system": [
          "dbs3"
        ],
        "ts": 1498504798.9530449
      },
      "das_id": [
        "59515e5ef4e3130af1ee3794"
      ],
      "file": [
        {
          "name": "/store/data/Run2016B/MET/RAW/v2/000/274/199/00000/C2770E37-BD26-E611-B330-02163E012449.root"
        }
      ],
      "qhash": "b8c58cd9320821e2473a7326cdf7de1d"
    },
    {
      "_id": "59515e5ef4e3130af1ee37ed",
      "cache_id": [
        "59515e5ef4e3130af1ee37b0"
      ],
      "das": {
        "api": [
          "file4DatasetRunLumi"
        ],
        "condition_keys": [
          "run.run_number",
          "dataset.name"
        ],
        "expire": 1498505098,
        "instance": "prod/global",
        "primary_key": "file.name",
        "record": 1,
        "services": [
          {
            "dbs3": [
              "dbs3"
            ]
          }
        ],
        "system": [
          "dbs3"
        ],
        "ts": 1498504798.9530449
      },
      "das_id": [
        "59515e5ef4e3130af1ee3794"
      ],
      "file": [
        {
          "name": "/store/data/Run2016B/MET/RAW/v2/000/274/199/00000/C459966B-BD26-E611-826B-02163E012604.root"
        }
      ],
      "qhash": "b8c58cd9320821e2473a7326cdf7de1d"
    },
    {
      "_id": "59515e5ef4e3130af1ee37ec",
      "cache_id": [
        "59515e5ef4e3130af1ee37ac"
      ],
      "das": {
        "api": [
          "file4DatasetRunLumi"
        ],
        "condition_keys": [
          "run.run_number",
          "dataset.name"
        ],
        "expire": 1498505098,
        "instance": "prod/global",
        "primary_key": "file.name",
        "record": 1,
        "services": [
          {
            "dbs3": [
              "dbs3"
            ]
          }
        ],
        "system": [
          "dbs3"
        ],
        "ts": 1498504798.9530449
      },
      "das_id": [
        "59515e5ef4e3130af1ee3794"
      ],
      "file": [
        {
          "name": "/store/data/Run2016B/MET/RAW/v2/000/274/199/00000/C6B8384A-BD26-E611-9A9E-02163E014594.root"
        }
      ],
      "qhash": "b8c58cd9320821e2473a7326cdf7de1d"
    },
    {
      "_id": "59515e5ef4e3130af1ee37eb",
      "cache_id": [
        "59515e5ef4e3130af1ee37a4"
      ],
      "das": {
        "api": [
          "file4DatasetRunLumi"
        ],
        "condition_keys": [
          "run.run_number",
          "dataset.name"
        ],
        "expire": 1498505098,
        "instance": "prod/global",
        "primary_key": "file.name",
        "record": 1,
        "services": [
          {
            "dbs3": [
              "dbs3"
            ]
          }
        ],
        "system": [
          "dbs3"
        ],
        "ts": 1498504798.9530449
      },
      "das_id": [
        "59515e5ef4e3130af1ee3794"
      ],
      "file": [
        {
          "name": "/store/data/Run2016B/MET/RAW/v2/000/274/199/00000/CC36864B-BD26-E611-B342-02163E014530.root"
        }
      ],
      "qhash": "b8c58cd9320821e2473a7326cdf7de1d"
    },
    {
      "_id": "59515e5ef4e3130af1ee37ea",
      "cache_id": [
        "59515e5ef4e3130af1ee37c6"
      ],
      "das": {
        "api": [
          "file4DatasetRunLumi"
        ],
        "condition_keys": [
          "run.run_number",
          "dataset.name"
        ],
        "expire": 1498505098,
        "instance": "prod/global",
        "primary_key": "file.name",
        "record": 1,
        "services": [
          {
            "dbs3": [
              "dbs3"
            ]
          }
        ],
        "system": [
          "dbs3"
        ],
        "ts": 1498504798.9530449
      },
      "das_id": [
        "59515e5ef4e3130af1ee3794"
      ],
      "file": [
        {
          "name": "/store/data/Run2016B/MET/RAW/v2/000/274/199/00000/D071A817-BD26-E611-8660-02163E0126FC.root"
        }
      ],
      "qhash": "b8c58cd9320821e2473a7326cdf7de1d"
    },
    {
      "_id": "59515e5ef4e3130af1ee37e9",
      "cache_id": [
        "59515e5ef4e3130af1ee37ba"
      ],
      "das": {
        "api": [
          "file4DatasetRunLumi"
        ],
        "condition_keys": [
          "run.run_number",
          "dataset.name"
        ],
        "expire": 1498505098,
        "instance": "prod/global",
        "primary_key": "file.name",
        "record": 1,
        "services": [
          {
            "dbs3": [
              "dbs3"
            ]
          }
        ],
        "system": [
          "dbs3"
        ],
        "ts": 1498504798.9530449
      },
      "das_id": [
        "59515e5ef4e3130af1ee3794"
      ],
      "file": [
        {
          "name": "/store/data/Run2016B/MET/RAW/v2/000/274/199/00000/D2E93F60-BD26-E611-96DF-02163E013452.root"
        }
      ],
      "qhash": "b8c58cd9320821e2473a7326cdf7de1d"
    },
    {
      "_id": "59515e5ef4e3130af1ee37e8",
      "cache_id": [
        "59515e5ef4e3130af1ee37b5"
      ],
      "das": {
        "api": [
          "file4DatasetRunLumi"
        ],
        "condition_keys": [
          "run.run_number",
          "dataset.name"
        ],
        "expire": 1498505098,
        "instance": "prod/global",
        "primary_key": "file.name",
        "record": 1,
        "services": [
          {
            "dbs3": [
              "dbs3"
            ]
          }
        ],
        "system": [
          "dbs3"
        ],
        "ts": 1498504798.9530449
      },
      "das_id": [
        "59515e5ef4e3130af1ee3794"
      ],
      "file": [
        {
          "name": "/store/data/Run2016B/MET/RAW/v2/000/274/199/00000/D6481415-BD26-E611-B6BB-02163E012BCA.root"
        }
      ],
      "qhash": "b8c58cd9320821e2473a7326cdf7de1d"
    },
    {
      "_id": "59515e5ef4e3130af1ee37e7",
      "cache_id": [
        "59515e5ef4e3130af1ee37ae"
      ],
      "das": {
        "api": [
          "file4DatasetRunLumi"
        ],
        "condition_keys": [
          "run.run_number",
          "dataset.name"
        ],
        "expire": 1498505098,
        "instance": "prod/global",
        "primary_key": "file.name",
        "record": 1,
        "services": [
          {
            "dbs3": [
              "dbs3"
            ]
          }
        ],
        "system": [
          "dbs3"
        ],
        "ts": 1498504798.9530449
      },
      "das_id": [
        "59515e5ef4e3130af1ee3794"
      ],
      "file": [
        {
          "name": "/store/data/Run2016B/MET/RAW/v2/000/274/199/00000/D831FD09-BD26-E611-ADE6-02163E0146D8.root"
        }
      ],
      "qhash": "b8c58cd9320821e2473a7326cdf7de1d"
    },
    {
      "_id": "59515e5ef4e3130af1ee37e6",
      "cache_id": [
        "59515e5ef4e3130af1ee37d3"
      ],
      "das": {
        "api": [
          "file4DatasetRunLumi"
        ],
        "condition_keys": [
          "run.run_number",
          "dataset.name"
        ],
        "expire": 1498505098,
        "instance": "prod/global",
        "primary_key": "file.name",
        "record": 1,
        "services": [
          {
            "dbs3": [
              "dbs3"
            ]
          }
        ],
        "system": [
          "dbs3"
        ],
        "ts": 1498504798.9530449
      },
      "das_id": [
        "59515e5ef4e3130af1ee3794"
      ],
      "file": [
        {
          "name": "/store/data/Run2016B/MET/RAW/v2/000/274/199/00000/DCB7898E-BD26-E611-991A-02163E0123A7.root"
        }
      ],
      "qhash": "b8c58cd9320821e2473a7326cdf7de1d"
    },
    {
      "_id": "59515e5ef4e3130af1ee37e5",
      "cache_id": [
        "59515e5ef4e3130af1ee37d5"
      ],
      "das": {
        "api": [
          "file4DatasetRunLumi"
        ],
        "condition_keys": [
          "run.run_number",
          "dataset.name"
        ],
        "expire": 1498505098,
        "instance": "prod/global",
        "primary_key": "file.name",
        "record": 1,
        "services": [
          {
            "dbs3": [
              "dbs3"
            ]
          }
        ],
        "system": [
          "dbs3"
        ],
        "ts": 1498504798.9530449
      },
      "das_id": [
        "59515e5ef4e3130af1ee3794"
      ],
      "file": [
        {
          "name": "/store/data/Run2016B/MET/RAW/v2/000/274/199/00000/E22E790E-BD26-E611-847C-02163E014534.root"
        }
      ],
      "qhash": "b8c58cd9320821e2473a7326cdf7de1d"
    },
    {
      "_id": "59515e5ef4e3130af1ee37e4",
      "cache_id": [
        "59515e5ef4e3130af1ee37b8"
      ],
      "das": {
        "api": [
          "file4DatasetRunLumi"
        ],
        "condition_keys": [
          "run.run_number",
          "dataset.name"
        ],
        "expire": 1498505098,
        "instance": "prod/global",
        "primary_key": "file.name",
        "record": 1,
        "services": [
          {
            "dbs3": [
              "dbs3"
            ]
          }
        ],
        "system": [
          "dbs3"
        ],
        "ts": 1498504798.9530449
      },
      "das_id": [
        "59515e5ef4e3130af1ee3794"
      ],
      "file": [
        {
          "name": "/store/data/Run2016B/MET/RAW/v2/000/274/199/00000/E2A0145B-BD26-E611-889B-02163E01443E.root"
        }
      ],
      "qhash": "b8c58cd9320821e2473a7326cdf7de1d"
    },
    {
      "_id": "59515e5ef4e3130af1ee37e3",
      "cache_id": [
        "59515e5ef4e3130af1ee37c7"
      ],
      "das": {
        "api": [
          "file4DatasetRunLumi"
        ],
        "condition_keys": [
          "run.run_number",
          "dataset.name"
        ],
        "expire": 1498505098,
        "instance": "prod/global",
        "primary_key": "file.name",
        "record": 1,
        "services": [
          {
            "dbs3": [
              "dbs3"
            ]
          }
        ],
        "system": [
          "dbs3"
        ],
        "ts": 1498504798.9530449
      },
      "das_id": [
        "59515e5ef4e3130af1ee3794"
      ],
      "file": [
        {
          "name": "/store/data/Run2016B/MET/RAW/v2/000/274/199/00000/F250435D-BD26-E611-80A2-02163E01461A.root"
        }
      ],
      "qhash": "b8c58cd9320821e2473a7326cdf7de1d"
    }
  ],
  "incache": true,
  "mongo_query": {
    "fields": [
      "file"
    ],
    "filters": {
      "grep": [
        "file.name"
      ],
      "sort": [],
      "unique": 1
    },
    "instance": "prod/global",
    "qcache": 0,
    "spec": {
      "dataset.name": "/MET/Run2016B-v2/RAW",
      "run.run_number": 274199
    }
  },
  "nresults": 53,
  "status": "ok",
  "timestamp": 1498504799.05
}